libsbml_draw/__init__.py
libsbml_draw/draw_network.py
libsbml_draw/layout.py
libsbml_draw/libsbml_draw.dll
libsbml_draw/libsbml_draw.dylib
libsbml_draw/libsbml_draw.so
libsbml_draw/network.py
libsbml_draw/render.py
libsbml_draw/sbml_layout.py
libsbml_draw/sbnw.py
libsbml_draw/styles.py
libsbml_draw/utils.py
libsbml_draw-1.1.0.dist-info/LICENCE
libsbml_draw-1.1.0.dist-info/LICENSE
libsbml_draw-1.1.0.dist-info/METADATA
libsbml_draw-1.1.0.dist-info/WHEEL
libsbml_draw-1.1.0.dist-info/top_level.txt
libsbml_draw-1.1.0.dist-info/RECORD
